{
  "projectId": "ai-code-assistant-concepts",
  "videoId": "13-instruction-layers",
  "runtimeSeconds": 42,
  "resolution": {
    "width": 1920,
    "height": 1080
  },
  "primaryObjective": "Instruction layers are the rule stack that shapes behavior before the model sees the task.",
  "shots": [
    {
      "id": "13-instruction-layers-shot-1",
      "timeRange": "0.0-8.4s",
      "beat": "open",
      "requiredOnScreenText": [
        "Instructions have precedence",
        "system",
        "project",
        "user"
      ],
      "visualFocus": "instructions metaphor with shared work packet and concept rail",
      "acceptance": [
        "Frame is nonblank and uses the active concept accent.",
        "Headline and three term chips are visible.",
        "Shared work packet appears before the bottom concept rail.",
        "The scene can be understood without voiceover."
      ]
    },
    {
      "id": "13-instruction-layers-shot-2",
      "timeRange": "8.4-16.8s",
      "beat": "define",
      "requiredOnScreenText": [
        "Conflicts must be explicit",
        "conflict",
        "priority",
        "resolve"
      ],
      "visualFocus": "instructions metaphor with shared work packet and concept rail",
      "acceptance": [
        "Frame is nonblank and uses the active concept accent.",
        "Headline and three term chips are visible.",
        "Shared work packet appears before the bottom concept rail.",
        "The scene can be understood without voiceover."
      ]
    },
    {
      "id": "13-instruction-layers-shot-3",
      "timeRange": "16.8-25.2s",
      "beat": "mechanism",
      "requiredOnScreenText": [
        "Local rules encode local reality",
        "repo",
        "style",
        "tests"
      ],
      "visualFocus": "instructions metaphor with shared work packet and concept rail",
      "acceptance": [
        "Frame is nonblank and uses the active concept accent.",
        "Headline and three term chips are visible.",
        "Shared work packet appears before the bottom concept rail.",
        "The scene can be understood without voiceover."
      ]
    },
    {
      "id": "13-instruction-layers-shot-4",
      "timeRange": "25.2-33.6s",
      "beat": "tradeoff",
      "requiredOnScreenText": [
        "Too many rules create fog",
        "stale",
        "noise",
        "route"
      ],
      "visualFocus": "instructions metaphor with shared work packet and concept rail",
      "acceptance": [
        "Frame is nonblank and uses the active concept accent.",
        "Headline and three term chips are visible.",
        "Shared work packet appears before the bottom concept rail.",
        "The scene can be understood without voiceover."
      ]
    },
    {
      "id": "13-instruction-layers-shot-5",
      "timeRange": "33.6-42.0s",
      "beat": "landing",
      "requiredOnScreenText": [
        "Promote stable patterns into skills",
        "pattern",
        "skill",
        "scope"
      ],
      "visualFocus": "instructions metaphor with shared work packet and concept rail",
      "acceptance": [
        "Frame is nonblank and uses the active concept accent.",
        "Headline and three term chips are visible.",
        "Shared work packet appears before the bottom concept rail.",
        "The scene can be understood without voiceover."
      ]
    }
  ]
}
